LinuxGongjuKuaisuJiaocheng/README.md
LinuxGongjuKuaisuJiaocheng/__init__.py
LinuxGongjuKuaisuJiaocheng/__main__.py
LinuxGongjuKuaisuJiaocheng/file.epub
LinuxGongjuKuaisuJiaocheng/index.html
LinuxGongjuKuaisuJiaocheng/css/__init__.py
LinuxGongjuKuaisuJiaocheng/css/annotations.css
LinuxGongjuKuaisuJiaocheng/css/main.css
LinuxGongjuKuaisuJiaocheng/css/normalize.css
LinuxGongjuKuaisuJiaocheng/css/popup.css
LinuxGongjuKuaisuJiaocheng/font/__init__.py
LinuxGongjuKuaisuJiaocheng/font/fontello.eot
LinuxGongjuKuaisuJiaocheng/font/fontello.svg
LinuxGongjuKuaisuJiaocheng/font/fontello.ttf
LinuxGongjuKuaisuJiaocheng/font/fontello.woff
LinuxGongjuKuaisuJiaocheng/img/__init__.py
LinuxGongjuKuaisuJiaocheng/img/annotator-glyph-sprite.png
LinuxGongjuKuaisuJiaocheng/img/annotator-icon-sprite.png
LinuxGongjuKuaisuJiaocheng/img/apple-touch-icon.png
LinuxGongjuKuaisuJiaocheng/img/cancelfullscreen.png
LinuxGongjuKuaisuJiaocheng/img/close.png
LinuxGongjuKuaisuJiaocheng/img/fullscreen.png
LinuxGongjuKuaisuJiaocheng/img/loader.gif
LinuxGongjuKuaisuJiaocheng/img/menu-icon.png
LinuxGongjuKuaisuJiaocheng/img/save.png
LinuxGongjuKuaisuJiaocheng/img/saved.png
LinuxGongjuKuaisuJiaocheng/img/settings-s.png
LinuxGongjuKuaisuJiaocheng/img/settings.png
LinuxGongjuKuaisuJiaocheng/img/star.png
LinuxGongjuKuaisuJiaocheng/js/__init__.py
LinuxGongjuKuaisuJiaocheng/js/epub.js
LinuxGongjuKuaisuJiaocheng/js/epub.min.js
LinuxGongjuKuaisuJiaocheng/js/epub.min.map
LinuxGongjuKuaisuJiaocheng/js/hooks.min.js
LinuxGongjuKuaisuJiaocheng/js/hooks.min.map
LinuxGongjuKuaisuJiaocheng/js/reader.js
LinuxGongjuKuaisuJiaocheng/js/reader.js.map
LinuxGongjuKuaisuJiaocheng/js/reader.min.js
LinuxGongjuKuaisuJiaocheng/js/reader.min.map
LinuxGongjuKuaisuJiaocheng/js/hooks/__init__.py
LinuxGongjuKuaisuJiaocheng/js/hooks/extensions/__init__.py
LinuxGongjuKuaisuJiaocheng/js/hooks/extensions/highlight.js
LinuxGongjuKuaisuJiaocheng/js/libs/__init__.py
LinuxGongjuKuaisuJiaocheng/js/libs/jquery.min.js
linux_gongju_kuaisu_jiaocheng-2024.3.1.0.dist-info/METADATA
linux_gongju_kuaisu_jiaocheng-2024.3.1.0.dist-info/WHEEL
linux_gongju_kuaisu_jiaocheng-2024.3.1.0.dist-info/entry_points.txt
linux_gongju_kuaisu_jiaocheng-2024.3.1.0.dist-info/top_level.txt
linux_gongju_kuaisu_jiaocheng-2024.3.1.0.dist-info/RECORD
